MANIFEST.in
README.MD
setup.py
calculator/__init__.py
calculator/calculate.py
chien_calculator.egg-info/PKG-INFO
chien_calculator.egg-info/SOURCES.txt
chien_calculator.egg-info/dependency_links.txt
chien_calculator.egg-info/top_level.txt