Metadata-Version: 2.1
Name: chien-calculator
Version: 0.0.1.1
Summary: Shows how to use setup.py
Home-page: https://www.domain.com
Author: Nguyen Hong Chien
License: GPLv3
Keywords: calculatortool
Platform: UNKNOWN
Classifier: Development Status :: 4 - Beta
Classifier: Intended Audience :: Developers
Classifier: Programming Language :: Python
Classifier: Programming Language :: Python :: 3.5
Classifier: Programming Language :: Python :: 3.6
Classifier: Programming Language :: Python :: 3.7
